threevis/__init__.py
threevis/context.py
threevis/immediate.py
threevis/indexed_attribute.py
threevis/mesh.py
threevis/mesh_helper.py
threevis/openmesh_utils.py
threevis-0.1.0.post25.dist-info/DESCRIPTION.rst
threevis-0.1.0.post25.dist-info/METADATA
threevis-0.1.0.post25.dist-info/RECORD
threevis-0.1.0.post25.dist-info/WHEEL
threevis-0.1.0.post25.dist-info/metadata.json
threevis-0.1.0.post25.dist-info/top_level.txt
