Metadata-Version: 2.0
Name: threevis
Version: 0.1.0.post25
Summary: Visualize meshes, point clouds, and other geometry in a Jupyter Notebook
Home-page: https://graphics.rwth-aachen.de:9000/threevis/threevis
Author: Dario Seyb, Isaak Lim, Janis Born
Author-email: isaak.lim@cs.rwth-aachen.de
License: BSD 3-Clause
Project-URL: Tracker, https://www.graphics.rwth-aachen.de:9000/threevis/threevis/issues
Project-URL: Source, https://www.graphics.rwth-aachen.de:9000/threevis/threevis
Platform: UNKNOWN
Classifier: Development Status :: 4 - Beta
Classifier: Programming Language :: Python :: 2
Classifier: Programming Language :: Python :: 3
Classifier: Topic :: Multimedia :: Graphics :: 3D Rendering
Requires-Dist: numpy
Requires-Dist: pythreejs (>=1.0.0)
